housing/__init__.py
housing/ingest_data.py
housing/main.py
housing/mlflow_utils.py
housing/score.py
housing/setup_logger.py
housing/sklearn_utils.py
housing/train.py
housing/transformers.py
housing_prediction_0.4-0.4.dist-info/LICENSE.txt
housing_prediction_0.4-0.4.dist-info/METADATA
housing_prediction_0.4-0.4.dist-info/WHEEL
housing_prediction_0.4-0.4.dist-info/top_level.txt
housing_prediction_0.4-0.4.dist-info/RECORD
