Metadata-Version: 2.1
Name: housing-prediction-0.4
Version: 0.4
Summary: A package to train machine learning models on housing dataset
Author-email: saiteja nuka <saiteja.nuka@tigeranalytics.com>
Project-URL: Homepage, https://github.com/TejaMl/mle-training
Project-URL: Bug Tracker, https://github.com/TejaMl/mle-training/issues
Classifier: Programming Language :: Python :: 3
Classifier: License :: OSI Approved :: MIT License
Classifier: Operating System :: OS Independent
Requires-Python: >=3.9
License-File: LICENSE.txt
